.gitignore
.gitmodules
CMakeLists.txt
LICENSE.txt
MANIFEST.in
README.md
pyproject.toml
requirements.txt
setup-dev.py
setup.cfg
setup.py
.github/workflows/conda-build.yml
.github/workflows/pypi-sdist.yml
doc/Makefile
doc/analyzer.txt
doc/applications.txt
doc/build_latex.txt
doc/conf.py
doc/dev_analyzer.txt
doc/dev_build.txt
doc/dev_comparator.txt
doc/dev_doc.txt
doc/dev_stroke-analyzer.txt
doc/index.txt
doc/make.bat
doc/run_comparator.txt
doc/run_editor.txt
doc/run_tests.txt
doc/sample-data.txt
doc/stopeight.txt
doc/theory.txt
doc/vector-graph.txt
doc/_extra/.nojekyll
doc/_extra/robots.txt
doc/_static/cliff.svg
doc/_static/crab.png
doc/_static/crest.svg
doc/_static/crest_or_sinusoid.svg
doc/_static/extraction_sequence.svg
doc/_static/function_graph.svg
doc/_static/sinus.svg
doc/_static/text.svg
doc/_static/vector_construction.svg
doc/_static/vector_graph.svg
doc/_static/vector_graph2.svg
doc/_static/vector_graph3.svg
doc/_templates/layout.html
doc/latex/Antis.tex
doc/latex/Not_Used.tex
doc/latex/Simulation.tex
doc/latex/Spline_Axioms.tex
doc/latex/Stopeight.bib
doc/latex/Stopeight_Analyzer.tex
doc/latex/Stopeight_Comparator.tex
doc/latex/Stopeight_Grapher.tex
doc/mathematica/Representation_Circles.m
doc/mathematica/Representation_Parallelogram.m
doc/mathematica/Spline.m
doc/mathematica/Spline_CharacteristicPolynomials.nb
doc/mathematica/Spline_EVConstraint.nb
doc/mathematica/Spline_Eigensystems.nb
doc/mathematica/Spline_Generative.nb
doc/mathematica/Spline_Pascal.nb
doc/mathematica/Spline_Representation.nb
doc/mathematica/SubSpaces.m
stopeight-clibs/CMakeLists.txt
stopeight-clibs/Includes.cmake
stopeight-clibs/Package.cmake
stopeight-clibs/Versioning.cmake
stopeight-clibs/analyzer/CMakeLists.txt
stopeight-clibs/analyzer/turns.cpp
stopeight-clibs/analyzer/turns.h
stopeight-clibs/analyzer/python/CMakeLists.txt
stopeight-clibs/analyzer/python/IFPyAnalyzer.cpp
stopeight-clibs/cmake-git-version-tracking/git_watcher.cmake
stopeight.egg-info/PKG-INFO
stopeight.egg-info/SOURCES.txt
stopeight.egg-info/dependency_links.txt
stopeight.egg-info/entry_points.txt
stopeight.egg-info/not-zip-safe
stopeight.egg-info/requires.txt
stopeight.egg-info/top_level.txt
